mtt/__init__.py
mtt/cache.py
mtt/cli.py
mtt/constants.py
mtt/utils.py
mgc_token_tools-0.1.2.dist-info/METADATA
mgc_token_tools-0.1.2.dist-info/WHEEL
mgc_token_tools-0.1.2.dist-info/entry_points.txt
mgc_token_tools-0.1.2.dist-info/top_level.txt
mgc_token_tools-0.1.2.dist-info/RECORD
