Metadata-Version: 2.4
Name: mgc-token-tools
Version: 0.1.2
Summary: Token management tools for the Microsoft Graph CLI (mgc)
Requires-Python: >=3.10
